bridgic/asl/__init__.py
bridgic/asl/_asl_automa.py
bridgic/asl/_canvas_object.py
bridgic/asl/_error.py
bridgic_asl-0.1.1.dist-info/METADATA
bridgic_asl-0.1.1.dist-info/WHEEL
bridgic_asl-0.1.1.dist-info/licenses/LICENSE
bridgic_asl-0.1.1.dist-info/RECORD
