Metadata-Version: 2.4
Name: bridgic-asl
Version: 0.1.1
Summary: ASL(Agent Structure Language) -- a powerful declarative DSL that embodies a component-oriented paradigm and is even capable of supporting dynamic topologies
Author-email: Tielei Zhang <zhangtl04@gmail.com>
License-File: LICENSE
Classifier: Programming Language :: Python :: 3
Classifier: Programming Language :: Python :: 3.9
Classifier: Programming Language :: Python :: 3.10
Classifier: Programming Language :: Python :: 3.11
Classifier: Programming Language :: Python :: 3.12
Classifier: Programming Language :: Python :: 3.13
Requires-Python: >=3.9
Requires-Dist: bridgic-core>=0.2.1
